ssri/__init__.py
ssri/ssri.py
ssri-0.0.7.dist-info/METADATA
ssri-0.0.7.dist-info/WHEEL
ssri-0.0.7.dist-info/entry_points.txt
ssri-0.0.7.dist-info/licenses/LICENSE.md
ssri-0.0.7.dist-info/RECORD
