Metadata-Version: 2.4
Name: ssri
Version: 0.0.7
Summary: A 2024 take on 2004 tech - effectively something that does what Apache Server Side Includes did, but at build time
Project-URL: Homepage, https://github.com/Sebagabones/Server-Side-Rendered-Includes
Author-email: Sebastian Gazey <bones@ucc.asn.au>
License:                     GNU AFFERO GENERAL PUBLIC LICENSE
License-File: LICENSE.md
Classifier: Development Status :: 4 - Beta
Classifier: License :: OSI Approved :: GNU Affero General Public License v3 or later (AGPLv3+)
Classifier: Operating System :: MacOS :: MacOS X
Classifier: Operating System :: POSIX :: Linux
Classifier: Programming Language :: Python :: 3
Classifier: Topic :: Software Development :: Build Tools
Classifier: Topic :: Software Development :: Code Generators
Requires-Python: >=3.8
